cob_eda-0.5.0.dist-info/METADATA
cob_eda-0.5.0.dist-info/WHEEL
cob_eda-0.5.0.dist-info/entry_points.txt
cob_eda/__init__.py
cob_eda/cli.py
cob_eda-0.5.0.dist-info/RECORD
