Metadata-Version: 2.1
Name: cob-eda
Version: 0.5.0
Summary: COB-EDA is a Python package designed to simplify exploratory data analysis with intuitive tools for statistics, visualizations, and insights discovery..
Author-Email: jacob-53 <jacob8753@gmail.com>
License: MIT
Requires-Python: >=3.10
Requires-Dist: pandas>=2.2.3
Requires-Dist: president-speech>=0.9.1
Requires-Dist: typer>=0.15.1
Requires-Dist: tqdm>=4.67.1
